setup.py
src/weblyzard_api/__init__.py
src/weblyzard_api.egg-info/PKG-INFO
src/weblyzard_api.egg-info/SOURCES.txt
src/weblyzard_api.egg-info/dependency_links.txt
src/weblyzard_api.egg-info/not-zip-safe
src/weblyzard_api.egg-info/requires.txt
src/weblyzard_api.egg-info/top_level.txt
src/weblyzard_api/client/__init__.py
src/weblyzard_api/client/annotator_client.py
src/weblyzard_api/client/classifier.py
src/weblyzard_api/client/domain_specificity.py
src/weblyzard_api/client/jeremia.py
src/weblyzard_api/client/jesaja.py
src/weblyzard_api/client/joanna.py
src/weblyzard_api/client/joanna_argparse.py
src/weblyzard_api/client/opinion_mining.py
src/weblyzard_api/client/pos.py
src/weblyzard_api/client/sentiment_analysis.py
src/weblyzard_api/client/videolyzard.py
src/weblyzard_api/client/wl_dictionaries.py
src/weblyzard_api/client/wl_rest_api.py
src/weblyzard_api/client/crowdflower/__init__.py
src/weblyzard_api/client/crowdflower/cml_builder.py
src/weblyzard_api/client/openrdf/__init__.py
src/weblyzard_api/client/openrdf/queries.py
src/weblyzard_api/client/openrdf/wl_upload_repository.py
src/weblyzard_api/client/projects/__init__.py
src/weblyzard_api/client/projects/media_criticism.py
src/weblyzard_api/client/recognize/__init__.py
src/weblyzard_api/test/__init__.py
src/weblyzard_api/xml_content/__init__.py
src/weblyzard_api/xml_content/parsers/__init__.py
src/weblyzard_api/xml_content/parsers/json_10.py
src/weblyzard_api/xml_content/parsers/xml_2005.py
src/weblyzard_api/xml_content/parsers/xml_2013.py
src/weblyzard_api/xml_content/parsers/xml_deprecated.py