Metadata-Version: 1.0
Name: weblyzard-api
Version: 0.5.6
Summary:  Web services for weblyzard
Home-page: UNKNOWN
Author: Heinz-Peter Lang and Albert Weichselbraun
Author-email: lang@weblyzard.com
License: UNKNOWN
Platform: UNKNOWN
